coolerspace/__init__.py
coolerspace/construction.py
coolerspace/exceptions.py
coolerspace/operation.py
coolerspace/spaces.py
coolerspace/transformation.py
coolerspace-1.0.1.dist-info/METADATA
coolerspace-1.0.1.dist-info/WHEEL
coolerspace-1.0.1.dist-info/RECORD
