Metadata-Version: 2.3
Name: coolerspace
Version: 1.0.1
Requires-Python: >=3.10
Requires-Dist: networkx
Requires-Dist: numpy
Requires-Dist: onnx
